microcalibrate/__init__.py
microcalibrate/calibration.py
microcalibrate/config.py
microcalibrate/evaluation.py
microcalibrate/hyperparameter_tuning.py
microcalibrate/main.py
microcalibrate/reweight.py
microcalibrate/utils/__init__.py
microcalibrate/utils/log_performance.py
microcalibrate/utils/metrics.py
microcalibrate-0.21.1.dist-info/METADATA
microcalibrate-0.21.1.dist-info/WHEEL
microcalibrate-0.21.1.dist-info/entry_points.txt
microcalibrate-0.21.1.dist-info/RECORD
